gearkits/__init__.py
gearkits/aws.py
gearkits/gitlab.py
gearkits/gsuite.py
gearkits/ipinio.py
gearkits/mattermost.py
gearkits/telegram.py
gearkits-0.6.0.dist-info/METADATA
gearkits-0.6.0.dist-info/WHEEL
gearkits-0.6.0.dist-info/RECORD
